CHANGES.txt
CONTRIBUTORS.txt
README.txt
setup.cfg
setup.py
collective/__init__.py
collective.transcode.recipe.egg-info/PKG-INFO
collective.transcode.recipe.egg-info/SOURCES.txt
collective.transcode.recipe.egg-info/dependency_links.txt
collective.transcode.recipe.egg-info/entry_points.txt
collective.transcode.recipe.egg-info/namespace_packages.txt
collective.transcode.recipe.egg-info/not-zip-safe
collective.transcode.recipe.egg-info/requires.txt
collective.transcode.recipe.egg-info/top_level.txt
collective/transcode/__init__.py
collective/transcode/recipe/__init__.py
collective/transcode/recipe/ctl.py
collective/transcode/recipe/tests/__init__.py
collective/transcode/recipe/tests/test_docs.py