Metadata-Version: 1.0
Name: collective.transcode.recipe
Version: 0.2
Summary: Recipe to setup a transcode daemon
Home-page: https://unweb.me
Author: unweb.me
Author-email: we@unweb.me
License: GPL
Keywords: video plone zope transcoding recipe
Platform: UNKNOWN
Classifier: Framework :: Buildout
Classifier: Intended Audience :: Developers
Classifier: Topic :: Software Development :: Build Tools
Classifier: Topic :: Software Development :: Libraries :: Python Modules
Classifier: License :: OSI Approved :: GNU General Public License (GPL)
